vtkio/__init__.py
vtkio/config.py
vtkio/helpers.py
vtkio/simplified.py
vtkio/utilities.py
vtkio/version.py
vtkio/vtk_cell_types.py
vtkio/vtk_structures.py
vtkio/reader/__init__.py
vtkio/reader/api.py
vtkio/reader/base_reader.py
vtkio/reader/compression.py
vtkio/reader/data_processors.py
vtkio/reader/exceptions.py
vtkio/reader/hdf5.py
vtkio/reader/readers.py
vtkio/reader/xml.py
vtkio/writer/__init__.py
vtkio/writer/pvd_writer.py
vtkio/writer/vtkhdf.py
vtkio/writer/writers.py
vtkio/writer/xml_writer.py
vtkio-0.1.0.dev9.dist-info/METADATA
vtkio-0.1.0.dev9.dist-info/WHEEL
vtkio-0.1.0.dev9.dist-info/licenses/LICENSE
vtkio-0.1.0.dev9.dist-info/RECORD
