Metadata-Version: 2.4
Name: VTKio
Version: 0.1.0.dev9
Summary: A simple package for converting data between VTK files (XML and HDF5) and NumPy arrays.
Project-URL: Homepage, https://jpmorr.gitlab.io/vtkio
Project-URL: Documentation, https://jpmorr.gitlab.io/vtkio
Project-URL: Issues, https://gitlab.com/jpmorr/vtkio/-/issues
Project-URL: Source, https://gitlab.com/jpmorr/vtkio/-/tree/main
Project-URL: Changelog, https://gitlab.com/jpmorr/vtkio/-/tree/main
Project-URL: donate, https://ko-fi.com/jpmorr
Author-email: JP Morrissey <morrissey.jp@gmail.com>
Maintainer-email: JP Morrissey <morrissey.jp@gmail.com>
License-Expression: BSD-3-Clause
License-File: LICENSE
Keywords: Converter,HDF5,NumPy,VTK,Visualisation,XML
Classifier: Development Status :: 4 - Beta
Classifier: Intended Audience :: Manufacturing
Classifier: Intended Audience :: Science/Research
Classifier: Operating System :: OS Independent
Classifier: Programming Language :: Python
Classifier: Programming Language :: Python :: 3 :: Only
Classifier: Programming Language :: Python :: 3.10
Classifier: Programming Language :: Python :: 3.11
Classifier: Programming Language :: Python :: 3.12
Classifier: Programming Language :: Python :: 3.13
Classifier: Programming Language :: Python :: Implementation :: CPython
Classifier: Topic :: Scientific/Engineering
Classifier: Topic :: Scientific/Engineering :: Visualization
Requires-Python: >=3.10
Requires-Dist: dotwiz>=0.4.0
Requires-Dist: h5py>=3.11
Requires-Dist: numpy>=2.1
Requires-Dist: pybase64>=1.3
Requires-Dist: xmltodict>=0.13
Provides-Extra: docs
Requires-Dist: markdown-exec[ansi]>=1.10.3; extra == 'docs'
Requires-Dist: mkdocs-autorefs>=1.4.2; extra == 'docs'
Requires-Dist: mkdocs-git-committers-plugin-2>=2.5.0; extra == 'docs'
Requires-Dist: mkdocs-git-revision-date-localized-plugin>=1.4.7; extra == 'docs'
Requires-Dist: mkdocs-material-extensions>=1.3.1; extra == 'docs'
Requires-Dist: mkdocs-material[imaging]>=9.6.14; extra == 'docs'
Requires-Dist: mkdocs>=1.6.1; extra == 'docs'
Requires-Dist: mkdocstrings-python>=0.18; extra == 'docs'
Requires-Dist: mkdocstrings>=0.29.1; extra == 'docs'
Requires-Dist: pipdeptree; extra == 'docs'
Provides-Extra: tests
Requires-Dist: pytest-cov>=6.1.1; extra == 'tests'
Requires-Dist: pytest>=8.3.5; extra == 'tests'
